zippa/__init__.py
zippa/cli.py
zippa/main.py
zippa/utils.py
zippa-0.1.2.dist-info/METADATA
zippa-0.1.2.dist-info/WHEEL
zippa-0.1.2.dist-info/entry_points.txt
zippa-0.1.2.dist-info/top_level.txt
zippa-0.1.2.dist-info/RECORD
