Metadata-Version: 2.4
Name: zippa
Version: 0.1.2
Summary: A Python utility for zipping directories and files
Author-email: Carlos Pumar-Frohberg <cpumarfrohberg@gmail.com>
License-Expression: MIT
Requires-Python: >=3.11
Requires-Dist: python-dotenv==1.1.0
Requires-Dist: pydantic>=2.6.1
Requires-Dist: typer>=0.16.0
